cockatoo_chain/__init__.py
cockatoo_chain/utils/model_a/__init__.py
cockatoo_chain/utils/model_a/base.py
cockatoo_chain/utils/model_a/gcp.py
cockatoo_chain/utils/model_a/open_ai.py
cockatoo_chain/utils/model_c/__init__.py
cockatoo_chain/utils/model_c/base.py
cockatoo_chain/utils/model_c/gcp.py
cockatoo_chain/utils/wrapper.py
cockatoo_chain-0.1.2.dist-info/METADATA
cockatoo_chain-0.1.2.dist-info/WHEEL
cockatoo_chain-0.1.2.dist-info/RECORD
