Metadata-Version: 2.3
Name: cockatoo-chain
Version: 0.1.2
Summary: The package is intended for STT, LLM and TSS models chaining.
Author: John Lee
Author-email: puremonkey2007@gmail.com
Requires-Python: >=3.9,<4.0
Classifier: Programming Language :: Python :: 3
Classifier: Programming Language :: Python :: 3.9
Classifier: Programming Language :: Python :: 3.10
Classifier: Programming Language :: Python :: 3.11
Classifier: Programming Language :: Python :: 3.12
Classifier: Programming Language :: Python :: 3.13
Requires-Dist: google-api-python-client (>=2.168.0,<3.0.0)
Requires-Dist: google-cloud-speech (>=2.32.0,<3.0.0)
Requires-Dist: google-cloud-texttospeech (>=2.26.0,<3.0.0)
Requires-Dist: langchain-core (>=0.3.51,<0.4.0)
Requires-Dist: langchain-openai (>=0.3.12,<0.4.0)
Requires-Dist: openai (>=1.67.0,<2.0.0)
Requires-Dist: pandas (>=2.2.3,<3.0.0)
Requires-Dist: python-dotenv (>=1.0.1,<2.0.0)
Requires-Dist: tqdm (>=4.67.1,<5.0.0)
